givenergy_modbus/__init__.py
givenergy_modbus/cli.py
givenergy_modbus/client.py
givenergy_modbus/decoder.py
givenergy_modbus/framer.py
givenergy_modbus/lut.py
givenergy_modbus/modbus.py
givenergy_modbus/model/__init__.py
givenergy_modbus/model/battery.py
givenergy_modbus/model/inverter.py
givenergy_modbus/model/plant.py
givenergy_modbus/model/register.py
givenergy_modbus/model/register_cache.py
givenergy_modbus/model/register_getter.py
givenergy_modbus/pdu.py
givenergy_modbus/transaction.py
givenergy_modbus/util.py
givenergy_modbus-0.10.1.dist-info/entry_points.txt
givenergy_modbus-0.10.1.dist-info/LICENSE
givenergy_modbus-0.10.1.dist-info/WHEEL
givenergy_modbus-0.10.1.dist-info/METADATA
givenergy_modbus-0.10.1.dist-info/RECORD
